deephaven/plugin/plotly/__init__.py
deephaven/plugin/plotly/figure_type.py
deephaven/plugin/plotly/theme_deephaven.py
deephaven_plugin_plotly-0.2.0.dist-info/LICENSE
deephaven_plugin_plotly-0.2.0.dist-info/METADATA
deephaven_plugin_plotly-0.2.0.dist-info/WHEEL
deephaven_plugin_plotly-0.2.0.dist-info/entry_points.txt
deephaven_plugin_plotly-0.2.0.dist-info/top_level.txt
deephaven_plugin_plotly-0.2.0.dist-info/RECORD
