Metadata-Version: 2.1
Name: deephaven-plugin-plotly
Version: 0.2.0
Summary: Deephaven Plugin for Plotly
Home-page: https://github.com/deephaven/deephaven-plugin-plotly
Author: Devin Smith, Vlad Babich
Author-email: vladbabich@deephaven.io
Project-URL: Source Code, https://github.com/deephaven/deephaven-plugin-plotly
Project-URL: Bug Tracker, https://github.com/deephaven/deephaven-plugin-plotly/issues
Keywords: deephaven,plugin,plotly
Platform: any
Classifier: Programming Language :: Python :: 3
Classifier: License :: OSI Approved :: Apache Software License
Classifier: Operating System :: OS Independent
Classifier: Environment :: Plugins
Classifier: Topic :: Scientific/Engineering :: Visualization
Classifier: Development Status :: 3 - Alpha
License-File: LICENSE
Requires-Dist: deephaven-plugin >=0.5.0
Requires-Dist: plotly
